agent_identity_cli/__init__.py
agent_identity_cli/cli.py
agent_identity_cli/core/__init__.py
agent_identity_cli/core/deployer.py
agent_identity_cli/core/models.py
agent_identity_cli/services/__init__.py
agent_identity_cli/services/identity_service.py
agent_identity_cli/services/ram_service.py
agent_identity_cli/utils/__init__.py
agent_identity_cli/utils/constants.py
agent_identity_cli/utils/credentials.py
agent_identity_cli-0.1.1.dist-info/METADATA
agent_identity_cli-0.1.1.dist-info/WHEEL
agent_identity_cli-0.1.1.dist-info/entry_points.txt
agent_identity_cli-0.1.1.dist-info/top_level.txt
agent_identity_cli-0.1.1.dist-info/RECORD
