Metadata-Version: 2.1
Name: agent-identity-cli
Version: 0.1.1
Summary: Agent Identity Toolkit CLI for managing AI Agent identities
Home-page: https://github.com/aliyun/agent-identity-dev-kit
Author: lingwu
Author-email: yangzankai.yzk@alibaba-inc.com
License: Apache-2.0
Keywords: alibabacloud,agent-identity,cli,ram,workload-identity
Classifier: Development Status :: 4 - Beta
Classifier: Intended Audience :: Developers
Classifier: License :: OSI Approved :: Apache Software License
Classifier: Programming Language :: Python :: 3
Classifier: Programming Language :: Python :: 3.10
Classifier: Programming Language :: Python :: 3.11
Classifier: Programming Language :: Python :: 3.12
Requires-Python: >=3.8
Requires-Dist: alibabacloud-agentidentity20250901 (>=0.0.1)
Requires-Dist: alibabacloud-credentials (>=0.3.0)
Requires-Dist: alibabacloud-ram20150501 (>=1.0.0)
Requires-Dist: alibabacloud-sts20150401 (>=1.0.0)
Requires-Dist: alibabacloud-tea-openapi (<1.0.0,>=0.4.1)
Requires-Dist: darabonba-core (<2.0.0,>=1.0.0)
Requires-Dist: rich (>=13.0.0)
Provides-Extra: dev
Requires-Dist: pytest-asyncio (>=0.21.0) ; extra == 'dev'
Requires-Dist: pytest (>=7.0.0) ; extra == 'dev'
